pytraeger/__init__.py
pytraeger/api.py
pytraeger/grill.py
pytraeger/manager.py
pytraeger/mqtt.py
pytraeger-0.5.dist-info/METADATA
pytraeger-0.5.dist-info/WHEEL
pytraeger-0.5.dist-info/top_level.txt
pytraeger-0.5.dist-info/RECORD
