Metadata-Version: 2.1
Name: pytraeger
Version: 0.5
Summary: Simple API to interact with the Traeger-Grill API
Author-email: Julian Schauder <pytraeger@schauder.info>
Project-URL: Homepage, https://github.com/zesoup/pytraeger
Project-URL: Bug Tracker, https://github.com/zesoup/pytraeger/issues
Classifier: Programming Language :: Python :: 3
Classifier: License :: OSI Approved :: MIT License
Classifier: Operating System :: OS Independent
Requires-Python: >=3.7
Requires-Dist: paho-mqtt
Requires-Dist: asyncio
Requires-Dist: psycopg2
Requires-Dist: requests
